tuir/__init__.py
tuir/__main__.py
tuir/__version__.py
tuir/clipboard.py
tuir/config.py
tuir/content.py
tuir/docs.py
tuir/exceptions.py
tuir/inbox_page.py
tuir/mime_parsers.py
tuir/oauth.py
tuir/objects.py
tuir/page.py
tuir/submission_page.py
tuir/subreddit_page.py
tuir/subscription_page.py
tuir/terminal.py
tuir/theme.py
tuir/packages/__init__.py
tuir/packages/praw/__init__.py
tuir/packages/praw/decorator_helpers.py
tuir/packages/praw/decorators.py
tuir/packages/praw/errors.py
tuir/packages/praw/handlers.py
tuir/packages/praw/helpers.py
tuir/packages/praw/internal.py
tuir/packages/praw/multiprocess.py
tuir/packages/praw/objects.py
tuir/packages/praw/praw.ini
tuir/packages/praw/settings.py
tuir/templates/index.html
tuir/templates/mailcap
tuir/templates/tuir.cfg
tuir/themes/colorblind-dark.cfg
tuir/themes/default.cfg.example
tuir/themes/molokai.cfg
tuir/themes/papercolor.cfg
tuir/themes/solarized-dark.cfg
tuir/themes/solarized-light.cfg
tuir-1.29.0.data/data/share/man/man1/tuir.1
tuir-1.29.0.dist-info/AUTHORS.rst
tuir-1.29.0.dist-info/LICENSE
tuir-1.29.0.dist-info/METADATA
tuir-1.29.0.dist-info/WHEEL
tuir-1.29.0.dist-info/entry_points.txt
tuir-1.29.0.dist-info/top_level.txt
tuir-1.29.0.dist-info/RECORD
